odoo/addons/stock_free_quantity/README.rst
odoo/addons/stock_free_quantity/__init__.py
odoo/addons/stock_free_quantity/__manifest__.py
odoo/addons/stock_free_quantity/i18n/it.po
odoo/addons/stock_free_quantity/i18n/stock_free_quantity.pot
odoo/addons/stock_free_quantity/models/__init__.py
odoo/addons/stock_free_quantity/models/product_template.py
odoo/addons/stock_free_quantity/readme/CONTRIBUTORS.rst
odoo/addons/stock_free_quantity/readme/DESCRIPTION.rst
odoo/addons/stock_free_quantity/static/description/icon.png
odoo/addons/stock_free_quantity/static/description/index.html
odoo/addons/stock_free_quantity/tests/__init__.py
odoo/addons/stock_free_quantity/tests/test_template_free_qty.py
odoo/addons/stock_free_quantity/views/product_product_view.xml
odoo/addons/stock_free_quantity/views/product_template_view.xml
odoo14_addon_stock_free_quantity-14.0.1.2.0.dist-info/METADATA
odoo14_addon_stock_free_quantity-14.0.1.2.0.dist-info/WHEEL
odoo14_addon_stock_free_quantity-14.0.1.2.0.dist-info/top_level.txt
odoo14_addon_stock_free_quantity-14.0.1.2.0.dist-info/RECORD
